tdmclient/__init__.py
tdmclient/__main__.py
tdmclient/atranspiler.py
tdmclient/atranspiler_warnings.py
tdmclient/client.py
tdmclient/clientasync.py
tdmclient/clientasynccachenode.py
tdmclient/clientasyncnode.py
tdmclient/clientnode.py
tdmclient/fb.py
tdmclient/module_clock.py
tdmclient/module_thymio.py
tdmclient/repl.py
tdmclient/server.py
tdmclient/serverws.py
tdmclient/tcp.py
tdmclient/thymio.py
tdmclient/util.py
tdmclient/ws.py
tdmclient/zeroconf.py
tdmclient/notebook/__init__.py
tdmclient/notebook/private-new.py
tdmclient/notebook/private.py
tdmclient/tools/__init__.py
tdmclient/tools/gui.py
tdmclient/tools/info.py
tdmclient/tools/list.py
tdmclient/tools/repl.py
tdmclient/tools/run.py
tdmclient/tools/sendevent.py
tdmclient/tools/server.py
tdmclient/tools/tdmdiscovery.py
tdmclient/tools/transpile.py
tdmclient/tools/watch.py
tdmclient-0.1.21.dist-info/LICENSE
tdmclient-0.1.21.dist-info/METADATA
tdmclient-0.1.21.dist-info/WHEEL
tdmclient-0.1.21.dist-info/top_level.txt
tdmclient-0.1.21.dist-info/RECORD
